trytond/modules/account_statement_matching_invoice/README.rst
trytond/modules/account_statement_matching_invoice/__init__.py
trytond/modules/account_statement_matching_invoice/statement.py
trytond/modules/account_statement_matching_invoice/tryton.cfg
trytond/modules/account_statement_matching_invoice/versiondep.txt
trytond/modules/account_statement_matching_invoice/locale/de.po
trytond/modules/account_statement_matching_invoice/locale/en.po
trytond/modules/account_statement_matching_invoice/tests/__init__.py
trytond/modules/account_statement_matching_invoice/tests/test_statement.py
mds_account_statement_matching_invoice-7.0.3.dist-info/METADATA
mds_account_statement_matching_invoice-7.0.3.dist-info/WHEEL
mds_account_statement_matching_invoice-7.0.3.dist-info/entry_points.txt
mds_account_statement_matching_invoice-7.0.3.dist-info/top_level.txt
mds_account_statement_matching_invoice-7.0.3.dist-info/RECORD
