Metadata-Version: 2.1
Name: mds-account-statement-matching-invoice
Version: 7.0.3
Summary: Tryton module for automatic matching of unpaid invoices when importing bank statements.
Home-page: https://www.m-ds.de/
Author: martin data - services
Author-email: service@m-ds.de
License: GPL-3
Keywords: tryton import account statement invoice matching
Platform: UNKNOWN
Classifier: Development Status :: 5 - Production/Stable
Classifier: Environment :: Plugins
Classifier: Framework :: Tryton
Classifier: Intended Audience :: Developers
Classifier: Intended Audience :: Customer Service
Classifier: Intended Audience :: Information Technology
Classifier: Topic :: Office/Business
Classifier: Natural Language :: German
Classifier: Natural Language :: English
Classifier: Operating System :: OS Independent
Classifier: License :: OSI Approved :: GNU General Public License (GPL)
Classifier: Programming Language :: Python :: 3.7
Classifier: Programming Language :: Python :: 3.8
Classifier: Programming Language :: Python :: 3.9
Requires-Dist: trytond (<7.1,>=7.0)
Requires-Dist: trytond-account-statement (<7.1,>=7.0)
